README.rst
setup.py
pytest_salt_containers.egg-info/PKG-INFO
pytest_salt_containers.egg-info/SOURCES.txt
pytest_salt_containers.egg-info/dependency_links.txt
pytest_salt_containers.egg-info/entry_points.txt
pytest_salt_containers.egg-info/requires.txt
pytest_salt_containers.egg-info/top_level.txt
saltcontainers/__init__.py
saltcontainers/clients.py
saltcontainers/factories.py
saltcontainers/models.py
saltcontainers/plugin.py
saltcontainers/utils.py